philosopherror/__init__.py
philosopherror/core.py
philosopherror/handlers.py
philosopherror/philosophers.py
philosopherror-0.1.0.dist-info/licenses/LICENSE
tests/__init__.py
tests/test_philosopherror.py
philosopherror-0.1.0.dist-info/METADATA
philosopherror-0.1.0.dist-info/WHEEL
philosopherror-0.1.0.dist-info/top_level.txt
philosopherror-0.1.0.dist-info/RECORD
