Metadata-Version: 2.4
Name: philosopherror
Version: 0.1.0
Summary: A Python library that provides philosophical wisdom when errors occur
Author-email: Not a Real Programmer <notarealprogrammer010@gmail.com>
License: MIT
Project-URL: Homepage, https://github.com/notarealprogrammer001/philosopherror
Project-URL: Bug Tracker, https://github.com/notarealprogrammer001/philosopherror/issues
Keywords: philosophy,error,exception,debug,wisdom
Classifier: Development Status :: 3 - Alpha
Classifier: Intended Audience :: Developers
Classifier: License :: OSI Approved :: MIT License
Classifier: Programming Language :: Python :: 3
Classifier: Programming Language :: Python :: 3.7
Classifier: Programming Language :: Python :: 3.8
Classifier: Programming Language :: Python :: 3.9
Classifier: Programming Language :: Python :: 3.10
Classifier: Programming Language :: Python :: 3.11
Classifier: Topic :: Software Development :: Libraries :: Python Modules
Classifier: Topic :: Software Development :: Debuggers
Requires-Python: >=3.7
License-File: LICENSE
Dynamic: license-file
Dynamic: requires-python
